chii/main.py
Chii-1.1.4.dist-info/METADATA
Chii-1.1.4.dist-info/WHEEL
Chii-1.1.4.dist-info/top_level.txt
Chii-1.1.4.dist-info/RECORD
