Metadata-Version: 2.1
Name: Chii
Version: 1.1.4
Summary: A minimal marketplace bot maker.
Requires-Dist: requests
Requires-Dist: python-telegram-bot (==13.15)
